dynpaac/__init__.py
dynpaac/dynamic_series_accessor.py
dynpaac-0.1.0.dist-info/LICENSE
dynpaac-0.1.0.dist-info/METADATA
dynpaac-0.1.0.dist-info/WHEEL
dynpaac-0.1.0.dist-info/RECORD
