Metadata-Version: 2.1
Name: dynpaac
Version: 0.1.0
Summary: Accessor for applying class methods and properties to Pandas Series.
License: MIT
Keywords: pandas,series,accessor,dynamic,pandas-extension,dynamic-accessor
Author: Christian Schreinemachers (Cs137)
Requires-Python: >=3.9
Classifier: Intended Audience :: Developers
Classifier: License :: OSI Approved :: MIT License
Classifier: Operating System :: OS Independent
Classifier: Programming Language :: Python :: 3
Classifier: Programming Language :: Python :: 3.9
Classifier: Programming Language :: Python :: 3.10
Classifier: Programming Language :: Python :: 3.11
Classifier: Programming Language :: Python :: 3.12
Classifier: Programming Language :: Python :: 3.13
Classifier: Programming Language :: Python :: 3 :: Only
Requires-Dist: pandas (>=2.2.3,<3.0.0)
Project-URL: Changelog, https://codeberg.org/Cs137/DynPaAc/src/branch/main/CHANGELOG.md
Project-URL: Issues, https://codeberg.org/Cs137/DynPaAc/issues
Project-URL: Repository, https://codeberg.org/Cs137/DynPaAc
